{
  "artifacts": {
    "log_path": "logs/latest_hourly_run.json",
    "notification_sent": true,
    "report_path": "reports/output/hourly_report.html"
  },
  "audit_summary": {
    "continuation_accepted_count": null,
    "continuation_audit_present": false,
    "continuation_rejected_count": null,
    "error_count": 0,
    "qualified_count": 0,
    "rejected_count": 0
  },
  "correlation": null,
  "generated_at": "2026-07-22T20:07:04Z",
  "generation_id": "hourly-20260722T200704Z",
  "macro_drivers": {
    "bitcoin": {
      "change_pct": -1.108541378149184,
      "level": 65778.8203125,
      "symbol": "BTC-USD"
    },
    "dollar": {
      "change_pct": -0.016806196568382854,
      "level": 101.1259994506836,
      "symbol": "DX-Y.NYB"
    },
    "gold": {
      "change_pct": 0.00966998775843308,
      "level": 4135.89990234375,
      "symbol": "GC=F"
    },
    "oil": {
      "change_pct": 1.3714755970262977,
      "level": 86.4800033569336,
      "symbol": "CL=F"
    },
    "rates": {
      "change_bps": 2.9182005799324946,
      "change_pct": 0.6266266994408085,
      "level": 4.6570000648498535,
      "symbol": "^TNX"
    },
    "silver": {
      "change_pct": -0.274681066032302,
      "level": 59.904998779296875,
      "symbol": "SI=F"
    },
    "volatility": {
      "change_pct": -1.1730138682710023,
      "level": 16.850000381469727,
      "symbol": "^VIX"
    }
  },
  "market_context": {
    "continuation_enabled": false,
    "data_quality": "ok",
    "expansion_regime": null,
    "imbalance_enabled": null,
    "stale_data_detected": false
  },
  "mode": "live",
  "outcome": "NO_TRADE",
  "regime": {
    "classification": "NEUTRAL",
    "confidence": 0.125,
    "net_score": -1,
    "neutral_votes": 5,
    "posture": "STAY_FLAT",
    "risk_off_votes": 2,
    "risk_on_votes": 1,
    "total_votes": 8,
    "vix_level": 16.850000381469727,
    "vix_pct_change": -0.011730138682710023,
    "vote_breakdown": {
      "BTC pct_change": "NEUTRAL",
      "DXY pct_change": "NEUTRAL",
      "IWM pct_change": "RISK_OFF",
      "QQQ pct_change": "RISK_OFF",
      "SPY pct_change": "NEUTRAL",
      "TNX pct_change": "NEUTRAL",
      "VIX level": "RISK_ON",
      "VIX pct_change": "NEUTRAL"
    }
  },
  "rejections": [],
  "schema_version": "v2",
  "session_date": "2026-07-22",
  "status": "STAY_FLAT",
  "system_state": {
    "confidence": 0.125,
    "intraday_state": null,
    "market_regime": "NEUTRAL",
    "router_mode": "MIXED",
    "stay_flat_reason": "STAY_FLAT posture",
    "time_gate_open": false,
    "tradable": false
  },
  "timezone": "America/New_York",
  "trade_candidates": []
}
