{"macro_drivers": {"volatility": {"symbol": "^VIX", "level": 19.780000686645508, "change_pct": 14.467592017702138}, "dollar": {"symbol": "DX-Y.NYB", "level": 101.34700012207031, "change_pct": 0.34157860681552804}, "rates": {"symbol": "^TNX", "level": 4.484999656677246, "change_pct": -0.5322725389374726, "change_bps": -2.387242154393291}, "bitcoin": {"symbol": "BTC-USD", "level": 62224.3203125, "change_pct": -2.6994098717296233}, "oil": {"symbol": "CL=F", "level": 72.83999633789062, "change_pct": -1.0863702585395034}, "gold": {"symbol": "GC=F", "level": 4152.10009765625, "change_pct": -0.24266246653932705}, "silver": {"symbol": "SI=F", "level": 62.13999938964844, "change_pct": -1.739409012686522}}, "generated_at": "2026-06-23T15:44:24Z"}