{"macro_drivers": {"volatility": {"symbol": "^VIX", "level": 16.170000076293945, "change_pct": 7.513298652307274}, "dollar": {"symbol": "DX-Y.NYB", "level": 101.1240005493164, "change_pct": 0.002965113068136035}, "rates": {"symbol": "^TNX", "level": 4.595000267028809, "change_pct": 0.569063275323535, "change_bps": 2.6148459020679313}, "bitcoin": {"symbol": "BTC-USD", "level": 62606.75, "change_pct": -1.7784195418887747}, "oil": {"symbol": "CL=F", "level": 74.55000305175781, "change_pct": 0.3499826800730672}, "gold": {"symbol": "GC=F", "level": 4025.39990234375, "change_pct": -1.0326007033583893}, "silver": {"symbol": "SI=F", "level": 58.474998474121094, "change_pct": -0.1451552205883167}}, "generated_at": "2026-07-13T15:39:20Z"}